dmsbbquery/__init__.py
dmsbbquery/businesspartnerdata.py
dmsbbquery/dmsbb.config
dmsbbquery/dmsbbquery.py
dmsbbquery/dummyinterface.py
dmsbbquery/getstock.py
dmsbbquery/shopdata.py
dmsbbquery/workshoporder.py
dmsbbquery-0.4.0.dist-info/METADATA
dmsbbquery-0.4.0.dist-info/WHEEL
dmsbbquery-0.4.0.dist-info/entry_points.txt
dmsbbquery-0.4.0.dist-info/licenses/LICENSE
dmsbbquery-0.4.0.dist-info/RECORD
