Metadata-Version: 2.4
Name: dmsbbquery
Version: 0.4.0
Summary: A Python interface for querying the DMS Backbone system via XML. Provides abstract base classes and concrete implementations to construct, send, and parse XML requests for dealer stock information, order data, business partner data and system availability.
Project-URL: Homepage, https://gitlab.com/chgaida/dmsbbquery/
Author-email: Christian Gaida <crish@mailbox.org>
License-Expression: MIT
License-File: LICENSE
Keywords: automotive,dealer management system,dms,query,vw,xml
Classifier: Operating System :: OS Independent
Classifier: Programming Language :: Python :: 3
Requires-Python: >=3.9
Requires-Dist: requests>=2.32.4
Provides-Extra: dev
Requires-Dist: black; extra == 'dev'
Requires-Dist: bumpver; extra == 'dev'
